richdaleai_mcp/__init__.py
richdaleai_mcp/__main__.py
richdaleai_mcp/server.py
richdaleai_mcp/utils.py
richdaleai_mcp-0.1.0.dist-info/licenses/LICENSE
richdaleai_mcp-0.1.0.dist-info/METADATA
richdaleai_mcp-0.1.0.dist-info/WHEEL
richdaleai_mcp-0.1.0.dist-info/entry_points.txt
richdaleai_mcp-0.1.0.dist-info/top_level.txt
richdaleai_mcp-0.1.0.dist-info/RECORD
