Metadata-Version: 2.4
Name: richdaleai-mcp
Version: 0.1.0
Summary: RichdaleAI MCP server for RunPod image generation
Author-email: Richdale AI <info@richdale.ai>
License: GNU Affero General Public License v3
Keywords: AI,image-generation,MCP,RunPod
Classifier: Programming Language :: Python :: 3
Classifier: Operating System :: OS Independent
Requires-Python: >=3.11
License-File: LICENSE
Requires-Dist: fastmcp
Requires-Dist: requests
Requires-Dist: python-dotenv
Dynamic: license-file
